qa_gen_cn/__init__.py
qa_gen_cn/generator.py
qa_gen_cn/llm_factory.py
qa_gen_cn/super_json.py
qa_gen_cn/utils.py
qa_gen_cn/validator.py
qagen-0.1.1.dist-info/METADATA
qagen-0.1.1.dist-info/WHEEL
qagen-0.1.1.dist-info/entry_points.txt
qagen-0.1.1.dist-info/licenses/LICENSE
qagen-0.1.1.dist-info/RECORD
