Metadata-Version: 2.4
Name: qagen
Version: 0.1.1
Summary: A powerful Chinese document QA pairs generation and validation tool with multiple LLM support
Project-URL: Homepage, https://github.com/crisschan/qa-gen-cn
Project-URL: Documentation, https://github.com/crisschan/qa-gen-cn#readme
Project-URL: Repository, https://github.com/crisschan/qa-gen-cn
Project-URL: Bug Tracker, https://github.com/crisschan/qa-gen-cn/issues
Project-URL: Source Code, https://github.com/crisschan/qa-gen-cn
Author-email: CrissChan <can101208@gmail.com>
License: MIT
License-File: LICENSE
Keywords: ai,chinese,document-processing,llm,nlp,qa-generation
Classifier: Development Status :: 4 - Beta
Classifier: Intended Audience :: Developers
Classifier: Intended Audience :: Science/Research
Classifier: License :: OSI Approved :: MIT License
Classifier: Operating System :: OS Independent
Classifier: Programming Language :: Python :: 3
Classifier: Programming Language :: Python :: 3.9
Classifier: Programming Language :: Python :: 3.10
Classifier: Programming Language :: Python :: 3.11
Classifier: Programming Language :: Python :: 3.12
Classifier: Topic :: Scientific/Engineering :: Artificial Intelligence
Classifier: Topic :: Software Development :: Libraries :: Python Modules
Classifier: Topic :: Text Processing :: Linguistic
Requires-Python: >=3.9
Requires-Dist: jieba>=0.42.1
Requires-Dist: langchain-community>=0.1.0
Requires-Dist: langchain-ollama>=0.1.0
Requires-Dist: langchain-openai>=0.1.0
Requires-Dist: langchain>=0.1.0
Requires-Dist: numpy<2.0
Requires-Dist: scikit-learn>=1.3.0
Requires-Dist: sentence-transformers>=2.2.0
Requires-Dist: torch>=2.0.0
Provides-Extra: dev
Requires-Dist: black>=23.0.0; extra == 'dev'
Requires-Dist: flake8>=6.0.0; extra == 'dev'
Requires-Dist: mypy>=1.0.0; extra == 'dev'
Requires-Dist: pytest-cov>=4.0.0; extra == 'dev'
Requires-Dist: pytest-mock>=3.10.0; extra == 'dev'
Requires-Dist: pytest>=7.0.0; extra == 'dev'
Provides-Extra: test
Requires-Dist: pytest-cov>=4.0.0; extra == 'test'
Requires-Dist: pytest-mock>=3.10.0; extra == 'test'
Requires-Dist: pytest>=7.0.0; extra == 'test'
